cipher_ey2335/__init__.py
cipher_ey2335/cipher_ey2335.py
cipher_ey2335-0.1.0.dist-info/LICENSE
cipher_ey2335-0.1.0.dist-info/WHEEL
cipher_ey2335-0.1.0.dist-info/METADATA
cipher_ey2335-0.1.0.dist-info/RECORD
