Metadata-Version: 2.1
Name: cipher-ey2335
Version: 0.1.0
Summary: A great package for hw07 by Ega Kurnia Yazid!
License: MIT
Author: Ega Kurnia Yazid
Requires-Python: >=3.9.1,<4.0.0
Classifier: License :: OSI Approved :: MIT License
Classifier: Programming Language :: Python :: 3
Classifier: Programming Language :: Python :: 3.10
Classifier: Programming Language :: Python :: 3.11
Requires-Dist: pytest (>=7.2.0,<8.0.0)
